cuppa/VERSION
cuppa/__init__.py
cuppa/__main__.py
cuppa/build_platform.py
cuppa/build_with_location.py
cuppa/build_with_package.py
cuppa/build_with_profile.py
cuppa/colourise.py
cuppa/configure.py
cuppa/construct.py
cuppa/location.py
cuppa/log.py
cuppa/output.py
cuppa/output_processor.py
cuppa/path.py
cuppa/progress.py
cuppa/recursive_glob.py
cuppa/timer.py
cuppa/tree.py
cuppa/version.py
cuppa/core/__init__.py
cuppa/core/base_options.py
cuppa/core/environment.py
cuppa/core/location_options.py
cuppa/core/options.py
cuppa/core/storage_options.py
cuppa/cpp/__init__.py
cuppa/cpp/create_version_file_cpp.py
cuppa/cpp/run_boost_test.py
cuppa/cpp/run_gcov_coverage.py
cuppa/cpp/run_patched_boost_test.py
cuppa/cpp/run_process_test.py
cuppa/cpp/templates/__init__.py
cuppa/cpp/templates/coverage_index.html
cuppa/dependencies/__init__.py
cuppa/dependencies/build_with_boost.py
cuppa/dependencies/build_with_qt4.py
cuppa/dependencies/build_with_qt5.py
cuppa/dependencies/build_with_quince.py
cuppa/dependencies/boost/__init__.py
cuppa/dependencies/boost/b2.py
cuppa/dependencies/boost/boost_bug_fix_1.73.0.diff
cuppa/dependencies/boost/boost_builder.py
cuppa/dependencies/boost/boost_exception.py
cuppa/dependencies/boost/boost_library_methods.py
cuppa/dependencies/boost/boost_test_patch_1.58.0.diff
cuppa/dependencies/boost/boost_test_patch_1.67.0.diff
cuppa/dependencies/boost/boost_test_patch_1.68.0.diff
cuppa/dependencies/boost/boost_test_patch_1.71.0.diff
cuppa/dependencies/boost/boost_test_patch_1.72.0.diff
cuppa/dependencies/boost/configjam.py
cuppa/dependencies/boost/library_dependencies.py
cuppa/dependencies/boost/library_naming.py
cuppa/dependencies/boost/patch_boost.py
cuppa/dependencies/boost/version_and_location.py
cuppa/method_helpers/__init__.py
cuppa/method_helpers/run_process.py
cuppa/methods/__init__.py
cuppa/methods/asciidoc_to_html.py
cuppa/methods/benchmark.py
cuppa/methods/build.py
cuppa/methods/build_benchmark.py
cuppa/methods/build_library.py
cuppa-0.9.153.dist-info/licenses/LICENSE_1_0.txt
cuppa-0.9.153.dist-info/METADATA
cuppa-0.9.153.dist-info/WHEEL
cuppa-0.9.153.dist-info/entry_points.txt
cuppa-0.9.153.dist-info/top_level.txt
cuppa-0.9.153.dist-info/RECORD
