Metadata-Version: 2.4
Name: cuppa
Version: 0.9.153
Summary: Cuppa, an extension package to simplify and extend Scons
Home-page: https://github.com/ja11sop/cuppa
Author: ja11sop
License: Boost Software License 1.0 - http://www.boost.org/LICENSE_1_0.txt
Keywords: scons,build,c++
Classifier: Topic :: Software Development :: Build Tools
Classifier: Intended Audience :: Developers
Classifier: Development Status :: 4 - Beta
Classifier: License :: OSI Approved
Classifier: Operating System :: OS Independent
Classifier: Programming Language :: Python :: 2
Classifier: Programming Language :: Python :: 3
License-File: LICENSE_1_0.txt
Requires-Dist: colorama
Requires-Dist: gcovr
Requires-Dist: grip
Requires-Dist: jinja2
Requires-Dist: libsass
Requires-Dist: lxml
Requires-Dist: psutil
Requires-Dist: pyscss
Requires-Dist: six
Requires-Dist: pyyaml
Dynamic: author
Dynamic: classifier
Dynamic: description
Dynamic: home-page
Dynamic: keywords
Dynamic: license
Dynamic: license-file
Dynamic: requires-dist
Dynamic: summary
